MyDecorators/MyDecoratorsClass.py
MyDecorators/__init__.py
MyDecorators-0.1.dist-info/LICENSE
MyDecorators-0.1.dist-info/METADATA
MyDecorators-0.1.dist-info/WHEEL
MyDecorators-0.1.dist-info/top_level.txt
MyDecorators-0.1.dist-info/RECORD
